{
  "id": "lem:322A",
  "kind": "lemma",
  "number": "322A",
  "name": "Methods of order 4",
  "is_helper": false,
  "chapter": 3,
  "section": "32",
  "subsection": "322",
  "subsection_title": "Methods of order 4",
  "page": 197,
  "statement_text": "If P and Q are each 3 × 3 matrices such that their product\nhas the form                           \n                            r11 r12 0\n                                       \n                    P Q =  r21 r22 0  ,\n                             0    0 0\nwhere                                                          !\n                                                 r11   r12\n                                     det                               \u0004= 0,\n                                                 r21   r22\nthen either the last row of P is zero or the last column of Q is zero.",
  "statement_latex": "\\begin{lemma}\nIf $P$ and $Q$ are each $3 \\times 3$ matrices such that their product has the form\n\\[\nPQ = \\begin{bmatrix}\nr_{11} & r_{12} & 0 \\\\\nr_{21} & r_{22} & 0 \\\\\n0 & 0 & 0\n\\end{bmatrix},\n\\]\nwhere\n\\[\n\\det \\begin{pmatrix}\nr_{11} & r_{12} \\\\\nr_{21} & r_{22}\n\\end{pmatrix} \\neq 0,\n\\]\nthen either the last row of $P$ is zero or the last column of $Q$ is zero.\n\\end{lemma}",
  "proof_text": "Proof. Because P Q is singular, either P is singular or Q is singular. In the\nfirst case, let u \u0004= 0 be such that u P = 0, and therefore u P Q = 0; in\nthe second case, let v \u0004= 0 be such that Qv = 0, and therefore P Qv = 0.\nBecause of the form of P Q, this implies that the first two components of u\n(or, respectively, the first two components of v) are zero.",
  "proof_latex": "\\begin{proof}\nBecause $PQ$ is singular, either $P$ is singular or $Q$ is singular. In the first case, let $u \\neq 0$ be such that $uP = 0$, and therefore $uPQ = 0$; in the second case, let $v \\neq 0$ be such that $Qv = 0$, and therefore $PQv = 0$. Because of the form of $PQ$, this implies that the first two components of $u$ (or, respectively, the first two components of $v$) are zero.\n\nTo obtain the result that $D(1)$ necessarily holds if $s = p = 4$, we apply\n\\end{proof}",
  "context_latex": "\\paragraph{Context}\nThe lemma is a standalone linear algebra statement about $3\\times 3$ matrices $P$ and $Q$, independent of the specific order condition calculations for Runge-Kutta methods discussed earlier.",
  "variables": [],
  "equations": [],
  "preamble": "The lemma is a standalone linear algebra statement about 3x3 matrices P and Q, independent of the specific order condition calculations for Runge-Kutta methods discussed earlier.",
  "introduces": [],
  "dependencies": [],
  "transitive_dependencies": [],
  "dependents": [],
  "lean_file": null,
  "lean_symbol": null,
  "formalization_status": "unformalized"
}