{
  "id": "lem:310B",
  "kind": "lemma",
  "number": "310B",
  "name": "Elementary Differential Weight Formula",
  "is_helper": false,
  "chapter": 3,
  "section": "31",
  "subsection": "310",
  "subsection_title": "Elementary differentials",
  "page": 173,
  "statement_text": "The value of (310i) is\n                               \u0014             r(t)\n                                     \u0019 h F (t)(y0 ),\n                                     θ(t)\n                                          σ(t)\n                               t∈T\n\nwhere θ\u0019 is defined by\n                             \n                             \n                              1,         t = τ,\n                      \u0019\n                      θ(t) =   \u001fk\n                             \n                                 θ(ti ), t = [t1 t2 · · · tk ].\n                                 i=1\n                                                                                      m\n                                                              1 t2 · · · tj ],",
  "statement_latex": "\\begin{lemma}\nThe value of \\eqref{eq:310i} is\n\\[\n\\sum_{t \\in T} \\frac{h^{\\rho(t)}}{\\sigma(t)} \\theta(t) F(t)(y_0),\n\\]\nwhere $\\theta$ is defined by\n\\[\n\\theta(t) = \n\\begin{cases}\n1, & t = \\tau, \\\\[4pt]\n\\displaystyle \\prod_{i=1}^{k} \\theta(t_i), & t = [t_1 t_2 \\cdots t_k].\n\\end{cases}\n\\]\n\\end{lemma}",
  "proof_text": "Proof. Use Theorem 306A. The case t = τ is obvious. For t = [tm 1 m2       j\n\n\nwhere t1 , t2 , . . . , tj are distinct, the factor",
  "proof_latex": "\\begin{proof}\nUse Theorem~\\ref{thm:306A}. The case $t = \\tau$ is obvious. For $t = [t_1^{m_1} t_2^{m_2} \\cdots t_j^{m_j}]$, where $t_1, t_2, \\dots, t_j$ are distinct, the factor\n\\[\n\\sigma(I) \\left( \\prod_{i=1}^{j} \\sigma(t_i)^{m_i} \\right)^{-1},\n\\]\nwhere $I$ is the index set consisting of $m_1$ copies of $1$, $m_2$ copies of $2$, \\dots, and $m_j$ copies of $j$, is equal to $\\sigma(t)^{-1}$.\n\\end{proof}",
  "context_latex": "\\paragraph{Context}\nThe lemma evaluates a formal series expressed in terms of rooted trees. The notation involves elementary differentials $F(t)$ and tree functions like order $r(t)$ and symmetry $\\sigma(t)$. The function $\\theta$ is defined recursively on tree structures.\n\nVariables:\n\\begin{itemize}\n    \\item $F(t)$: the elementary differential associated with the tree $t$\n    \\item $y_0$: initial condition for the ODE\n    \\item $h$: step size\n    \\item $T$: set of rooted trees\n    \\item $r(t)$: order of the tree $t$\n    \\item $\\sigma(t)$: symmetry of the tree $t$\n    \\item $\\tau$: the elementary tree (a single node)\n\\end{itemize}\n\nReferenced equation:\n\\begin{equation}\n    \\text{(310i)}: \\quad \\sum_{t \\in T} \\frac{h^{r(t)}}{\\sigma(t)} F(t)(y_0)\n\\end{equation}",
  "variables": [
    {
      "name": "F",
      "definition": "F(t) is the elementary differential associated with the tree t"
    },
    {
      "name": "y0",
      "definition": "initial condition for the ODE"
    },
    {
      "name": "h",
      "definition": "step size"
    },
    {
      "name": "T",
      "definition": "set of rooted trees"
    },
    {
      "name": "r(t)",
      "definition": "order of the tree t"
    },
    {
      "name": "σ(t)",
      "definition": "symmetry of the tree t"
    },
    {
      "name": "τ",
      "definition": "the elementary tree (a single node)"
    }
  ],
  "equations": [
    {
      "tag": "310i",
      "content": "the formal series expression being evaluated"
    }
  ],
  "preamble": "The lemma evaluates a formal series (310i) expressed in terms of rooted trees. The notation involves elementary differentials F(t) and tree functions like order r(t) and symmetry σ(t). The function θ is defined recursively on tree structures.",
  "introduces": [],
  "dependencies": [
    {
      "id": "thm:306A",
      "kind": "theorem",
      "number": "306A",
      "name": "Taylor’s theorem",
      "edge_type": "uses_theorem",
      "context": "Theorem 306A"
    },
    {
      "id": "def:310A",
      "kind": "definition",
      "number": "310A",
      "name": "elementary differential",
      "edge_type": "uses_equation_from",
      "context": "(310i) owned by def:310A"
    }
  ],
  "transitive_dependencies": [
    "def:310A",
    "thm:301A",
    "thm:306A",
    "thm:311B"
  ],
  "dependents": [
    "lem:311A",
    "lem:312B",
    "lem:313A",
    "thm:311D",
    "thm:317A"
  ],
  "lean_file": null,
  "lean_symbol": null,
  "formalization_status": "unformalized"
}