{
  "id": "thm:342C",
  "kind": "theorem",
  "number": "342C",
  "name": "Gaussian Quadrature Order Conditions Equivalence",
  "is_helper": false,
  "chapter": 3,
  "section": "33",
  "subsection": "342",
  "subsection_title": "Methods based on Gaussian quadrature",
  "page": 238,
  "statement_text": "G(2s) ⇒ B(2s),                          (342j)\n                                      G(2s) ⇒ E(s, s),                       (342k)\n                        B(2s) ∧ C(s) ∧ D(s) ⇒ G(2s),                          (342l)\n                               B(2s) ∧ C(s) ⇒ E(s, s),                      (342m)\n                                B(2s) ∧ E(s, s) ⇒ C(s),                     (342n)\n                                 B(2s) ∧ D(s) ⇒ E(s, s),                    (342o)\n                                B(2s) ∧ E(s, s) ⇒ D(s).                     (342p)",
  "statement_latex": "\\begin{theorem}\n\\begin{gather}\nG(2s) \\Rightarrow B(2s), \\label{eq:342j} \\\\\nG(2s) \\Rightarrow E(s, s), \\label{eq:342k} \\\\\nB(2s) \\land C(s) \\land D(s) \\Rightarrow G(2s), \\label{eq:342l} \\\\\nB(2s) \\land C(s) \\Rightarrow E(s, s), \\label{eq:342m} \\\\\nB(2s) \\land E(s, s) \\Rightarrow C(s), \\label{eq:342n} \\\\\nB(2s) \\land D(s) \\Rightarrow E(s, s), \\label{eq:342o} \\\\\nB(2s) \\land E(s, s) \\Rightarrow D(s). \\label{eq:342p}\n\\end{gather}\n\\end{theorem}",
  "proof_text": "Proof. The first two results (342j), (342k) are consequences of the order\nconditions. Given that C(s) is true, all order conditions based on trees\ncontaining the structure · · · [τ k−1 ] · · · , with k ≤ s, can be removed, as we\n\n\n\n\n                                    C(s)\n\n                                                                     G(2s)\n                           ∧           ∧\n\n                                              E(s, s)\n                  B(2s)                                         ∧\n\n                                                 ∧\n                           ∧\n\n                                    D(s)\n\n\n              Figure 342(i)     Schema representing Theorem 342C\n\n\n\nsaw in Subsection 321. Similarly, the condition D(s) enables us to remove\nfrom consideration all trees of the form [τ k−1 [· · · ]]. Hence, if both C(s) and\nD(s) are true, the only trees remaining are those associated with the trees\ncovered by B(2s). Hence, (342l) follows. Multiply the matrix of quantities\nthat must be zero according to the C(s) condition\n          \"               \"                             \"                     \n              j a1j − c1       a1j cj − 12 c21    ···                 − 1s cs1\n                                                                  s−1\n                                                          j a1j cj\n          \"               \"j                            \"                     \n            j a2j − c2       j a2j cj − 2 c2      ···                 − 1s cs2 \n                                         1 2                      s−1\n                                                         j a2j cj\n                                                                              \n                ..                ..                              ..          \n                 .                 .                               .          \n           \"               \"                             \"\n             j asj − cs      j asj cj − 2 cs      ···                 − s cs\n                                        1 2                       s−1   1 s\n                                                           j asj cj\n\nby the non-singular matrix\n                                                                \n                            b1         b2        ···       bs\n                                                                \n                        b1 c1       b2 c2       ···     bs cs \n                                                                \n                            ..         ..                  ..   \n                             .          .                   .   \n                         b1 cs−1\n                              1     b2 cs−1\n                                         2       ···    bs css−1\n\n\nand the result is the matrix of E(s, s) conditions. Hence, (342m) follows and,\nbecause the matrix multiplier is non-singular, (342n) also follows. The final\nresults (342o) and (342p) are proved in similar way.",
  "proof_latex": "\\begin{proof}\nThe first two results \\eqref{eq:342j}, \\eqref{eq:342k} are consequences of the order conditions. Given that $C(s)$ is true, all order conditions based on trees containing the structure $\\cdots [\\tau^{k-1}] \\cdots$, with $k \\leq s$, can be removed, as we saw in Subsection~321. Similarly, the condition $D(s)$ enables us to remove from consideration all trees of the form $[\\tau^{k-1} [\\cdots]]$. Hence, if both $C(s)$ and $D(s)$ are true, the only trees remaining are those associated with the trees covered by $B(2s)$. Hence, \\eqref{eq:342l} follows. Multiply the matrix of quantities that must be zero according to the $C(s)$ condition\n\\[\n\\begin{bmatrix}\n\\sum_j a_{1j} - c_1 & \\sum_j a_{1j} c_j - \\frac{1}{2} c_1^2 & \\cdots & \\sum_j a_{1j} c_j^{s-1} - \\frac{1}{s} c_1^s \\\\\n\\sum_j a_{2j} - c_2 & \\sum_j a_{2j} c_j - \\frac{1}{2} c_2^2 & \\cdots & \\sum_j a_{2j} c_j^{s-1} - \\frac{1}{s} c_2^s \\\\\n\\vdots & \\vdots & \\ddots & \\vdots \\\\\n\\sum_j a_{sj} - c_s & \\sum_j a_{sj} c_j - \\frac{1}{2} c_s^2 & \\cdots & \\sum_j a_{sj} c_j^{s-1} - \\frac{1}{s} c_s^s\n\\end{bmatrix}\n\\]\nby the non-singular matrix\n\\[\n\\begin{bmatrix}\nb_1 & b_2 & \\cdots & b_s \\\\\nb_1 c_1 & b_2 c_2 & \\cdots & b_s c_s \\\\\n\\vdots & \\vdots & \\ddots & \\vdots \\\\\nb_1 c_1^{s-1} & b_2 c_2^{s-1} & \\cdots & b_s c_s^{s-1}\n\\end{bmatrix}\n\\]\nand the result is the matrix of $E(s, s)$ conditions. Hence, \\eqref{eq:342m} follows and, because the matrix multiplier is non-singular, \\eqref{eq:342n} also follows. The final results \\eqref{eq:342o} and \\eqref{eq:342p} are proved in a similar way.\n\nA schema summarizing Theorem~342C is shown in Figure~342(i). To turn this result into a recipe for constructing methods of order $2s$ we have:\n\\end{proof}",
  "context_latex": "\\paragraph{Context}\nThe theorem concerns relationships between order conditions for Runge--Kutta methods. The notation \\(G(\\eta)\\) indicates a method of order \\(\\eta\\), while \\(B\\), \\(C\\), \\(D\\), and \\(E\\) are specific sets of simplifying conditions. The context involves analyzing whether \\(C(s)\\) and \\(D(s)\\) can be satisfied simultaneously given quadrature conditions.\n\nVariables:\n\\begin{itemize}\n    \\item \\(G(\\eta)\\): represents that a given Runge--Kutta method has order \\(\\eta\\)\n    \\item \\(B(2s)\\): order conditions for Runge--Kutta methods, specifically the quadrature conditions up to order \\(2s\\)\n    \\item \\(C(s)\\): simplifying conditions related to the internal stages of the Runge--Kutta method\n    \\item \\(D(s)\\): simplifying conditions related to the internal stages of the Runge--Kutta method\n    \\item \\(E(s, s)\\): a condition given by equation (321c) that links \\(C(s)\\) and \\(D(s)\\)\n\\end{itemize}\n\nReferenced equations:\n\\begin{itemize}\n    \\item (321c): equation defining \\(E(s, s)\\) (exact form not provided in the preceding text, but it is referenced as the link between \\(C(s)\\) and \\(D(s)\\))\n\\end{itemize}",
  "variables": [
    {
      "name": "G(η)",
      "definition": "represents that a given Runge–Kutta method has order η"
    },
    {
      "name": "B(2s)",
      "definition": "order conditions for Runge–Kutta methods, specifically the quadrature conditions up to order 2s"
    },
    {
      "name": "C(s)",
      "definition": "simplifying conditions related to the internal stages of the Runge–Kutta method"
    },
    {
      "name": "D(s)",
      "definition": "simplifying conditions related to the internal stages of the Runge–Kutta method"
    },
    {
      "name": "E(s, s)",
      "definition": "a condition given by equation (321c) that links C(s) and D(s)"
    }
  ],
  "equations": [
    {
      "tag": "321c",
      "content": "equation defining E(s, s) (exact form not provided in the preceding text, but it is referenced as the link between C(s) and D(s))"
    }
  ],
  "preamble": "The theorem concerns relationships between order conditions for Runge–Kutta methods. The notation G(η) indicates a method of order η, while B, C, D, and E are specific sets of simplifying conditions. The context involves analyzing whether C(s) and D(s) can be satisfied simultaneously given quadrature conditions.",
  "introduces": [],
  "dependencies": [],
  "transitive_dependencies": [],
  "dependents": [
    "cor:342D",
    "cor:359B",
    "lem:342A",
    "lem:342B",
    "lem:359A",
    "thm:324C",
    "thm:358A",
    "thm:363A"
  ],
  "lean_file": null,
  "lean_symbol": null,
  "formalization_status": "unformalized"
}